openapi_client/__init__.py
openapi_client/api_client.py
openapi_client/api_response.py
openapi_client/configuration.py
openapi_client/exceptions.py
openapi_client/py.typed
openapi_client/rest.py
openapi_client/api/__init__.py
openapi_client/api/activities_api.py
openapi_client/api/activity_descriptions_api.py
openapi_client/api/activity_rates_api.py
openapi_client/api/allocations_api.py
openapi_client/api/bank_accounts_api.py
openapi_client/api/bank_transactions_api.py
openapi_client/api/bank_transfers_api.py
openapi_client/api/bill_themes_api.py
openapi_client/api/billable_clients_api.py
openapi_client/api/billable_matters_api.py
openapi_client/api/billing_settings_api.py
openapi_client/api/bills_api.py
openapi_client/api/calendar_entries_api.py
openapi_client/api/calendar_entry_event_types_api.py
openapi_client/api/calendar_visibilities_api.py
openapi_client/api/calendars_api.py
openapi_client/api/civil_certificated_rates_api.py
openapi_client/api/civil_controlled_rates_api.py
openapi_client/api/clients_api.py
openapi_client/api/clio_payments_links_api.py
openapi_client/api/clio_payments_payments_api.py
openapi_client/api/comments_api.py
openapi_client/api/communications_api.py
openapi_client/api/contacts_api.py
openapi_client/api/conversation_messages_api.py
openapi_client/api/conversations_api.py
openapi_client/api/credit_memos_api.py
openapi_client/api/criminal_controlled_rates_api.py
openapi_client/api/currencies_api.py
openapi_client/api/custom_actions_api.py
openapi_client/api/custom_field_sets_api.py
openapi_client/api/custom_fields_api.py
openapi_client/api/damages_api.py
openapi_client/api/document_archives_api.py
openapi_client/api/document_automations_api.py
openapi_client/api/document_categories_api.py
openapi_client/api/document_templates_api.py
openapi_client/api/document_versions_api.py
openapi_client/api/documents_api.py
openapi_client/api/event_metrics_api.py
openapi_client/api/expense_categories_api.py
openapi_client/api/folders_api.py
clio_openapi_client-1.0.0.dist-info/METADATA
clio_openapi_client-1.0.0.dist-info/WHEEL
clio_openapi_client-1.0.0.dist-info/top_level.txt
clio_openapi_client-1.0.0.dist-info/RECORD
