Metadata-Version: 2.1
Name: clio-openapi-client
Version: 1.0.0
Summary: Clio API Documentation
Home-page: 
Author: Clio API Support
Author-email: api@clio.com
Keywords: OpenAPI,OpenAPI-Generator,Clio API Documentation
Requires-Dist: urllib3 <3.0.0,>=1.25.3
Requires-Dist: python-dateutil >=2.8.2
Requires-Dist: pydantic >=2
Requires-Dist: typing-extensions >=4.7.1
